Workbook

Sheet Datos
B2: cifras en millones de pesos | C2: Banco del Pacífico
B3: Efectivo y reservas en el banco central | C3: 450
B4: Títulos conservados a vencimiento | C4: =SUM(C5:C9) -> 670
B5: Bonos gubernamentales < 1 año (Nivel 1 para HQLA) | C5: 180
B6: Bondes 1-5 años (Nivel 1 para HQLA) | C6: 240
B7: Bonos M 1-5 años (Nivel 2A para HQLA) | C7: 150
B8: Bonos corporativos calif AA- o superior tasa fija (Nivel 2A para HQLA) | C8: 100
B9: Bonos corporativos calif BBB- a A+ tasa fija (nivel 2B para HQLA) | C9: 0
B10: Cartera de crédito | C10: =SUM(C11:C15) -> 6500
B11: Hipotecario | C11: 1500
B12: Consumo (tarjetas de crédito, de nómina, personales) | C12: 2500
B13: PYMES | C13: 800
B14: Corporativo (grandes empresas) | C14: 1200
B15: Instituciones Financieras (sofoms, sofipos, sapis, otros bancos) | C15: 500
B16: Activos Fijos | C16: 330
B17: Otros activos | C17: 48
B18: TOTAL ACTIVO | C18: =C3+C4+C10+C16+C17 -> 7998
B19: Depósitos a la vista | C19: =C20+C21 -> 2700
B20: Minoristas (retail)a | C20: 2100
B21: De empresasb | C21: 600
B22: Depósitos a plazo | C22: =C23+C24 -> 2300
B23: Minoristas (retail) | C23: 1900
B24: De empresas | C24: 400
B25: Fondeo mayoristac | C25: 750
B26: Bonos emitidos con vencimiento < 1 año | C26: 400
B27: Bonos emitidos con vencimiento 1-5 años | C27: 1000
B28: Bonos emitidos con vencimiento 5-10 años | C28: 0
B29: TOTAL PASIVO | C29: =C19+C22+C25+C26+C27+C28 -> 7150
B30: Capital Tier 1d | C30: 848
B31: Capital Tier 2e | C31: 0
B32: TOTAL CAPITAL | C32: =C30+C31 -> 848
B33: TOTAL PASIVO Y CAPITAL | C33: =C29+C32 -> 7998

Sheet LCR
B2: LCR | C2: =F12/G37 -> 1.1079836
B4: HQLA
B6: Tipo | C6: Descripción | D6: Ponderación | E6: Monto | F6: Monto Factorizado
B7: Nivel 1 | C7: Efectivo y reservas en el banco central | D7: 1 | E7: =Datos!C3 -> 450 | F7: =E7*D7 -> 450
B8: Nivel 1 | C8: Bonos gubernamentales < 1 año o duración menor a 1 | D8: 1 | E8: =Datos!C5+Datos!C6 -> 420 | F8: =E8*D8 -> 420
B9: Nivel 2A | C9: Bonos soberanos >1 año | D9: 0.85 | E9: =Datos!C7 -> 150 | F9: =E9*D9 -> 127.5
B10: Nivel 2A | C10: Bonos corporativos calif AA- o superior | D10: 0.85 | E10: =Datos!C8 -> 100 | F10: =E10*D10 -> 85
B11: Nivel 2B | C11: Bonos corporativos calif BBB- a A+ | D11: 0.5 | E11: =Datos!C9 -> 0 | F11: =E11*D11 -> 0
E12: TOTAL | F12: =SUM(F7:F11) -> 1082.5
B14: SALIDAS NETAS DE EFECTIVO
C16: Descripción | D16: Factor | E16: Ponderaciones | F16: Monto | G16: Monto Factorizado
C17: VISTA
C18: Depósitos minoristas core (vista) | D18: 0.03 | E18: 0.6 | F18: =LCR!E18*Datos!C20 -> 1260 | G18: =F18*D18 -> 37.8
C19: Depósitos minoristas menos estables (vista) | D19: 0.1 | E19: =1-E18 -> 0.4 | F19: =E19*Datos!C20 -> 840 | G19: =F19*D19 -> 84
C20: Depósitos operacionales de empresas (vista) | D20: 0.25 | E20: 0.2 | F20: =E20*Datos!C21 -> 120 | G20: =F20*D20 -> 30
C21: Depósitos no operacionales de empresas (vista) | D21: 0.4 | E21: =1-E20 -> 0.8 | F21: =E21*Datos!C21 -> 480 | G21: =F21*D21 -> 192
C22: Depósitos operacioneles de financieras (vista) | D22: 1 | E22: 0.5 | F22: 0 | G22: =F22*D22 -> 0
C23: Depósitos no operacioneles de financieras (vista) | D23: 1 | E23: 0.5 | F23: 0 | G23: =F23*D23 -> 0
C24: PLAZO
C25: Depósitos minoristas core (plazo) | D25: 0.03 | E25: =E18 -> 0.6 | F25: =E25*Datos!C23 -> 1140 | G25: =F25*D25 -> 34.2
C26: Depósitos minoristas menos estables (plazo) | D26: 0.1 | E26: =E19 -> 0.4 | F26: =E26*Datos!C23 -> 760 | G26: =F26*D26 -> 76
C27: Depósitos operacionales de empresas (plazo) | D27: 0.25 | E27: =E20 -> 0.2 | F27: =E27*Datos!C24 -> 80 | G27: =F27*D27 -> 20
C28: Depósitos no operacionales de empresas (plazo) | D28: 0.4 | E28: =E21 -> 0.8 | F28: =E28*Datos!C24 -> 320 | G28: =F28*D28 -> 128
C29: Depósitos operacioneles de financieras (plazo) | D29: 1 | E29: 0.5 | F29: 0 | G29: =F29*D29 -> 0
C30: Depósitos no operacioneles de financieras (plazo) | D30: 1 | E30: 0.5 | F30: 0 | G30: =F30*D30 -> 0
C31: FONDEO MAYORISTA
C32: Fondeo mayorista garantizado con HQLA Nivel 1 contraparte no financiera | D32: 0 | E32: 0 | F32: =E32*Datos!$C$25 -> 0 | G32: =F32*D31 -> 0
C33: Fondeo mayorista garantizado con HQLA Nivel 1 contraparte financiera | D33: 0 | E33: 0.5 | F33: =E33*Datos!$C$25 -> 375 | G33: =F33*D32 -> 0
C34: Fondeo mayorista garantizado con HQLA Nivel 2A contraparte no financiera | D34: 0.15 | E34: 0 | F34: =E34*Datos!$C$25 -> 0 | G34: =F34*D34 -> 0
C35: Fondeo mayorista garantizado con HQLA Nivel 2A contraparte financiera | D35: 0.25 | E35: 0 | F35: =E35*Datos!$C$25 -> 0 | G35: =F35*D35 -> 0
C36: Fondeo mayorista sin colateral (sin garantía) | D36: 1 | E36: 0.5 | F36: =E36*Datos!$C$25 -> 375 | G36: =F36*D36 -> 375
F37: TOTAL | G37: =SUM(G18:G23,G25:G30,G33:G36) -> 977

Sheet NSFR
B2: NSFR | C2: =F18/F33 -> 1.4370026
B4: ASF
C6: Descripción | D6: Factor | E6: Monto | F6: Monto Factorizado
C7: Capital Tier 1 y Tier 2 | D7: 1 | E7: =Datos!C32 -> 848 | F7: =D7*E7 -> 848
C8: Pasivos con plazo residual mayor a 1 año | D8: 1 | E8: =Datos!C27+Datos!C28 -> 1000 | F8: =D8*E8 -> 1000
C9: Depósitos minoristas estables (core) | D9: 0.95 | E9: =LCR!F18+LCR!F25 -> 2400 | F9: =D9*E9 -> 2280
C10: Depósitos minoristas menos estables (volátiles) | D10: 0.9 | E10: =LCR!F19+LCR!F26 -> 1600 | F10: =D10*E10 -> 1440
C11: Depósitos operacionales de empresas no financieras | D11: 0.75 | E11: =LCR!F20+LCR!F27 -> 200 | F11: =D11*E11 -> 150
C12: Depósitos no operacionales de empresas no financieras | D12: 0 | E12: =LCR!F21+LCR!F28 -> 800 | F12: =D12*E12 -> 0
C13: Depósitos operacionales de empresas financieras | D13: 0.5 | E13: =LCR!F22+LCR!F29 -> 0 | F13: =D13*E13 -> 0
C14: Depósitos no operacionales de empresas financieras | D14: 0 | E14: =LCR!F23+LCR!F30 -> 0 | F14: =D14*E14 -> 0
C15: Fondeo mayorista contrapartes no financieras con colateral | D15: 0.6 | E15: =LCR!F32+LCR!F34 -> 0 | F15: =D15*E15 -> 0
C16: Fondeo mayorista contrapartes financieras con colateral | D16: 0.4 | E16: =LCR!F33+LCR!F35 -> 375 | F16: =D16*E16 -> 150
C17: Fondeo mayorista sin colateral | D17: 0 | E17: =LCR!F36 -> 375 | F17: =D17*E17 -> 0
E18: TOTAL | F18: =SUM(F7:F17) -> 5868
B21: RSF
C23: Descripción | D23: Factor | E23: Monto | F23: Monto Factorizado
C24: Efectivo y depósitos en el banco central | D24: 0 | E24: =LCR!E7 -> 450 | F24: =E24*D24 -> 0
C25: HQLA nivel 1 | D25: 0.05 | E25: =LCR!E8 -> 420 | F25: =E25*D25 -> 21
C26: HQLA nivel 2A | D26: 0.15 | E26: =LCR!E9+LCR!E10 -> 250 | F26: =E26*D26 -> 37.5
C27: HQLA nivel 2B | D27: 0.5 | E27: =LCR!E11 -> 0 | F27: =E27*D27 -> 0
C28: Hipotecarios | D28: 0.65 | E28: =Datos!C11 -> 1500 | F28: =E28*D28 -> 975
C29: Créditos a consumo | D29: 0.5 | E29: =Datos!C12 -> 2500 | F29: =E29*D29 -> 1250
C30: Créditos PYME | D30: 0.65 | E30: =Datos!C13 -> 800 | F30: =E30*D30 -> 520
C31: Créditos a empresas no financieras (corporativos) largo plazo | D31: 0.65 | E31: =Datos!C14 -> 1200 | F31: =E31*D31 -> 780
C32: Créditos a instituciones financieras (largo plazo) | D32: 1 | E32: =Datos!C15 -> 500 | F32: =E32*D32 -> 500
E33: TOTAL | F33: =SUM(F24:F32) -> 4083.5

Sheet NII
B2: TIIE | C2: 0.07
B3: TIIE Fondeo | C3: 0.0674
B5: Total Ingresos | C5: =SUM(E11:E23) -> 1358.132
B6: Total Egresos | C6: =SUM(E28:E36) -> 400.75
B7: NII | C7: =C5-C6 -> 957.382
B8: ROE | C8: =C7/C40 -> 1.1289882
B10: cifras en millones de pesos | C10: Banco del Pacífico | D10: Tasa | E10: Ingresos
B11: Efectivo y reservas en el banco central | C11: 450 | D11: 0 | E11: =C11*D11 -> 0
B12: Títulos conservados a vencimiento | C12: =SUM(C13:C17) -> 670
B13: Bonos gubernamentales < 1 año (Nivel 1 para HQLA) | C13: 180 | D13: 0.075 | E13: =C13*D13 -> 13.5
B14: Bondes 1-5 años (Nivel 1 para HQLA) | C14: 240 | D14: =C3+0.0019 -> 0.0693 | E14: =C14*D14 -> 16.632
B15: Bonos M 1-5 años (Nivel 2A para HQLA) | C15: 150 | D15: 0.085 | E15: =C15*D15 -> 12.75
B16: Bonos corporativos calif AA- o superior tasa fija (Nivel 2A para HQLA) | C16: 100 | D16: 0.09 | E16: =C16*D16 -> 9
B17: Bonos corporativos calif BBB- a A+ tasa fija (nivel 2B para HQLA) | C17: 0 | D17: 0.095 | E17: =C17*D17 -> 0
B18: Cartera de crédito | C18: =SUM(C19:C23) -> 6500
B19: Hipotecario | C19: 1500 | D19: 0.1075 | E19: =C19*D19 -> 161.25
B20: Consumo (tarjetas de crédito, de nómina, personales) | C20: 2500 | D20: =0.6*(C2+0.36)+0.4*(0.19) -> 0.334 | E20: =C20*D20 -> 835
B21: PYMES | C21: 800 | D21: =C2+0.09 -> 0.16 | E21: =C21*D21 -> 128
B22: Corporativo (grandes empresas) | C22: 1200 | D22: =C2+0.04 -> 0.11 | E22: =C22*D22 -> 132
B23: Instituciones Financieras (sofoms, sofipos, sapis, otros bancos) | C23: 500 | D23: =C2+0.03 -> 0.1 | E23: =C23*D23 -> 50
B24: Activos Fijos | C24: 330
B25: Otros activos | C25: 48
B26: TOTAL ACTIVO | C26: =C11+C12+C18+C24+C25 -> 7998 | E26: Egresos
B27: Depósitos a la vista | C27: =C28+C29 -> 2700
B28: Minoristas (retail)a | C28: 2100 | D28: 0.04 | E28: =C28*D28 -> 84
B29: De empresasb | C29: 600 | D29: 0.04 | E29: =C29*D29 -> 24
B30: Depósitos a plazo | C30: =C31+C32 -> 2300
B31: Minoristas (retail) | C31: 1900 | D31: 0.05 | E31: =C31*D31 -> 95
B32: De empresas | C32: 400 | D32: 0.0525 | E32: =C32*D32 -> 21
B33: Fondeo mayoristac | C33: 750 | D33: 0.065 | E33: =C33*D33 -> 48.75
B34: Bonos emitidos con vencimiento < 1 año | C34: 400 | D34: =C2 -> 0.07 | E34: =C34*D34 -> 28
B35: Bonos emitidos con vencimiento 1-5 años | C35: 1000 | D35: 0.1 | E35: =C35*D35 -> 100
B36: Bonos emitidos con vencimiento 5-10 años | C36: 0 | D36: 0.0875 | E36: =C36*D36 -> 0
B37: TOTAL PASIVO | C37: =C27+C30+C33+C34+C35+C36 -> 7150
B38: Capital Tier 1d | C38: 848
B39: Capital Tier 2e | C39: 0
B40: TOTAL CAPITAL | C40: =C38+C39 -> 848
B41: TOTAL PASIVO Y CAPITAL | C41: =C37+C40 -> 7998

Sheet DELTA NII
B1: Cambio de Tasa (pb) | C1: -50
B2: Cambio de Tasa (%) | C2: =C1/10000 -> -0.005
B4: Total Ingresos | C4: =SUM(F10:F22) -> -21.2
B5: Total Egresos | C5: =SUM(F27:F35) -> -24
B6: NII | C6: =C4-C5 -> 2.8
B7: Tipo de Empresa | C7: =IF(OR(AND(C1>0,C6<0),AND(C1<0,C6>0)),"LIABILITY SENSITIVE","ASSET SENSITIVE") -> LIABILITY SENSITIVE
B9: cifras en millones de pesos | C9: Banco del Pacífico | D9: Variable? | E9: Factor | F9: Ingresos
B10: Efectivo y reservas en el banco central | C10: 450 | D10: 0
B11: Títulos conservados a vencimiento | C11: =SUM(C12:C16) -> 670
B12: Bonos gubernamentales < 1 año (Nivel 1 para HQLA) | C12: 180 | D12: 0
B13: Bondes 1-5 años (Nivel 1 para HQLA) | C13: 240 | D13: 1 | E13: 1 | F13: =E13*D13*C13*$C$2 -> -1.2
B14: Bonos M 1-5 años (Nivel 2A para HQLA) | C14: 150 | D14: 0
B15: Bonos corporativos calif AA- o superior tasa fija (Nivel 2A para HQLA) | C15: 100 | D15: 0
B16: Bonos corporativos calif BBB- a A+ tasa fija (nivel 2B para HQLA) | C16: 0 | D16: 0
B17: Cartera de crédito | C17: =SUM(C18:C22) -> 6500
B18: Hipotecario | C18: 1500 | D18: 0
B19: Consumo (tarjetas de crédito, de nómina, personales) | C19: 2500 | D19: 1 | E19: 0.6 | F19: =E19*D19*C19*$C$2 -> -7.5
B20: PYMES | C20: 800 | D20: 1 | E20: 1 | F20: =E20*D20*C20*$C$2 -> -4
B21: Corporativo (grandes empresas) | C21: 1200 | D21: 1 | E21: 1 | F21: =E21*D21*C21*$C$2 -> -6
B22: Instituciones Financieras (sofoms, sofipos, sapis, otros bancos) | C22: 500 | D22: 1 | E22: 1 | F22: =E22*D22*C22*$C$2 -> -2.5
B23: Activos Fijos | C23: 330
B24: Otros activos | C24: 48
B25: TOTAL ACTIVO | C25: =C10+C11+C17+C23+C24 -> 7998 | F25: Egresos
B26: Depósitos a la vista | C26: =C27+C28 -> 2700
B27: Minoristas (retail)a | C27: 2100 | D27: 1 | E27: 0.5 | F27: =E27*D27*C27*$C$2 -> -5.25
B28: De empresasb | C28: 600 | D28: 1 | E28: 0.5 | F28: =E28*D28*C28*$C$2 -> -1.5
B29: Depósitos a plazo | C29: =C30+C31 -> 2300
B30: Minoristas (retail) | C30: 1900 | D30: 1 | E30: 1 | F30: =E30*D30*C30*$C$2 -> -9.5
B31: De empresas | C31: 400 | D31: 1 | E31: 1 | F31: =E31*D31*C31*$C$2 -> -2
B32: Fondeo mayoristac | C32: 750 | D32: 1 | E32: 1 | F32: =E32*D32*C32*$C$2 -> -3.75
B33: Bonos emitidos con vencimiento < 1 año | C33: 400 | D33: 1 | E33: 1 | F33: =E33*D33*C33*$C$2 -> -2
B34: Bonos emitidos con vencimiento 1-5 años | C34: 1000 | D34: 0
B35: Bonos emitidos con vencimiento 5-10 años | C35: 0 | D35: 0
B36: TOTAL PASIVO | C36: =C26+C29+C32+C33+C34+C35 -> 7150
B37: Capital Tier 1d | C37: 848
B38: Capital Tier 2e | C38: 0
B39: TOTAL CAPITAL | C39: =C37+C38 -> 848
B40: TOTAL PASIVO Y CAPITAL | C40: =C36+C39 -> 7998
