Workbook

Sheet balance
B2: BANCO 1 | G2: BANCO 2
B3: Activo | D3: Pasivo | G3: Activo | I3: Pasivo
B4: Reservas en BC | C4: 300 | D4: Depositos a la vista | E4: 3800 | G4: Reservas en BC | H4: 200 | I4: Depositos a la vista | J4: 2400 | L4: Considerar entradas y salids de flujo:
B5: Deuda Gub. CP | C5: 500 | D5: Depósito a plazo | E5: 1500 | G5: Deuda Gub. CP | H5: 400 | I5: Depósito a plazo | J5: 3100 | L5: a) en condiciones normales
B6: Cartera Crédito | G6: Cartera Crédito | I6: Prestamos interbancarios | J6: 600 | L6: b) en condiciones de estrés
B7: Tarjetas Cred. | C7: 1000 | D7: Capital | G7: Tarjetas Cred. | H7: 1800 | I7: Capital
B8: Personales (1-3 a) | C8: 600 | D8: Capital social | E8: 1000 | G8: Personales (1-3 a) | H8: 1200 | I8: Capital social | J8: 1000
B9: Automotriz (2-5 a) | C9: 1400 | D9: Utilidades retenidas | E9: 200 | G9: Automotriz (2-5 a) | H9: 0 | I9: Utilidades retenidas | J9: 200
B10: PYMES (1 a 5a) | C10: 2500 | G10: PYMES (1 a 5a) | H10: 3700
B12: TOTAL ACTIVO | C12: =SUM(C4:C10) -> 6300 | D12: TOTAL PASIVO Y CAPITAL | E12: =SUM(E4:E10) -> 6500 | G12: TOTAL ACTIVO | H12: =SUM(H4:H10) -> 7300 | I12: TOTAL PASIVO Y CAPITAL | J12: =SUM(J4:J10) -> 7300
B15: BANCO 3 | G15: BANCO 4
B16: Activo | D16: Pasivo | G16: Activo | I16: Pasivo
B17: Reservas en BC | C17: 100 | D17: Depositos a la vista | E17: 1400 | G17: Reservas en BC | H17: 400 | I17: Depositos a la vista | J17: 1900
B18: Deuda Gub. CP | C18: 300 | D18: Depósito a plazo | E18: 500 | G18: Deuda Gub. CP | H18: 1000 | I18: Depósito a plazo | J18: 1300
B19: Cartera Crédito | D19: Préstamos interbancarios | E19: 0 | G19: Cartera Crédito | I19: Préstamos interbancarios | J19: 400
B20: Tarjetas Cred. | C20: 500 | D20: Bonos emitidos (3-5-10 a) | E20: 2400 | G20: Tarjetas Cred. | H20: 1100 | I20: Bonos emitidos (3-5-10 a) | J20: 2000
B21: Personales (1-3 a) | C21: 1200 | D21: Capital | G21: Personales (1-3 a) | H21: 1500 | I21: Capital
B22: Hipotecarios (20 a) | C22: 2500 | D22: Capital social | E22: 1000 | G22: Hipotecarios (20 a) | H22: 2000 | I22: Capital social | J22: 2000
B23: PYMES (1 a 5a) | C23: 900 | D23: Utilidades retenidas | E23: 200 | G23: PYMES (1 a 5a) | H23: 1800 | I23: Utilidades retenidas | J23: 200
B25: TOTAL ACTIVO | C25: =SUM(C17:C23) -> 5500 | D25: TOTAL PASIVO Y CAPITAL | E25: =SUM(E17:E23) -> 5500 | G25: TOTAL ACTIVO | H25: =SUM(H17:H23) -> 7800 | I25: TOTAL PASIVO Y CAPITAL | J25: =SUM(J17:J23) -> 7800

Sheet resultados
C1: Banco 1 | D1: Banco 2 | E1: Banco 3 | F1: Banco 4
B2: Ingreso por intereses
A3: 0.07 | B3: Reservas en BC | C3: =A3*balance!C4 -> 21 | D3: =A3*balance!H4 -> 14 | E3: =A3*balance!C17 -> 7 | F3: =A3*balance!H17 -> 28 | H3: ¿Cuánto tener en reservas en BC y en deuda gubernamental de corto plazo?
A4: 0.065 | B4: Deuda Gub. CP | C4: =A4*[1]baance!C5 -> #REF! | D4: =A4*balance!H5 -> 26 | E4: =A4*balance!C18 -> 19.5 | F4: =A4*balance!H18 -> 65 | H4: Cubrir al menos 100% mis salidas de efectivo a 30 días
A5: 0.48 | B5: Tarjetas Cred. | C5: =A5*balance!C7 -> 480 | D5: =A5*balance!H7 -> 864 | E5: =A5*balance!C20 -> 240 | F5: =A5*balance!H20 -> 528
A6: 0.24 | B6: Personales | C6: =A6*balance!C8 -> 144 | D6: =A6*balance!H8 -> 288 | E6: =A6*balance!C21 -> 288 | F6: =A6*balance!H21 -> 360 | H6: ¿Si incluyo algo de bonos gubernamentales de largo plazo o de bonos corporativos?
A7: 0.1 | B7: Automotriz | C7: =A7*balance!C9 -> 140 | D7: =A7*balance!H9 -> 0 | E7: 0 | F7: =A7*balance!H22 -> 200 | H7: Dependes de la volatilidad de las tasas
A8: 0.16 | B8: PYMES | C8: =A8*balance!C10 -> 400 | D8: =A8*balance!H10 -> 592 | E8: =A8*balance!C23 -> 144 | F8: =A8*balance!H23 -> 288
A9: 0.11 | B9: Hipotecarios | C9: 0 | D9: 0 | E9: =balance!C22*A9 -> 275 | F9: 0 | H9: ¿A qué segmento de negocio me quiero enfocar? ¿cuál es más rentable y menos riesgo (credito y liquidez)?
B10: Total ingreso intereses | C10: =SUM(C3:C8) -> #REF! | D10: =SUM(D3:D8) -> 1784 | E10: =SUM(E3:E8) -> 698.5 | F10: =SUM(F3:F8) -> 1469
B12: Costo por intereses
A13: 0 | B13: Depósitos a la vista | C13: =A13*balance!E4 -> 0 | D13: =A13*balance!J4 -> 0 | E13: =A13*balance!E17 -> 0 | F13: =A13*balance!J17 -> 0
A14: 0.05 | B14: Depósitos a plazo | C14: =A14*balance!E5 -> 75 | D14: =A14*balance!J5 -> 155 | E14: =A14*balance!E18 -> 25 | F14: =A14*balance!J18 -> 65
A15: 0.069 | B15: Préstamos Interbanc. | C15: 0 | D15: =A15*balance!J6 -> 41.4 | E15: =A15*balance!E19 -> 0 | F15: =A15*balance!J19 -> 27.6
A16: 0.09 | B16: Bonos emitidos | C16: 0 | D16: 0 | E16: =A16*balance!E20 -> 216 | F16: =A16*balance!J20 -> 180 | H16: ¿Cómo me voy a fondear? ¿Lo máximo a la vista o un mix entre vista y a plazo fijo?
B17: Total costo por intereses | C17: =SUM(C13:C16) -> 75 | D17: =SUM(D13:D16) -> 196.4 | E17: =SUM(E13:E16) -> 241 | F17: =SUM(F13:F16) -> 272.6
H18: ¿Voy a utilizar el mercado interbancario?
B19: Margen financiero | C19: =C10-C17 -> #REF! | D19: =D10-D17 -> 1587.6 | E19: =E10-E17 -> 457.5 | F19: =F10-F17 -> 1196.4 | H19: ¿Voy a emitir deuda a 3 años o a 10 años, a tasa fija o a tasa variable?
B20: ROE | C20: =C19/(balance!E8+balance!E9) -> #REF! | D20: =D19/(balance!J8+balance!J9) -> 1.323 | E20: =E19/(balance!E22+balance!E23) -> 0.38125 | F20: =F19/(balance!J22+balance!J23) -> 0.54381818
H23: ¿Qué tanto capital requiero? ¿En exceso obtengo un ROE bajo, de menos elevo mi nivel de riesgo financiero?
