Workbook

Sheet Datos
B2: cifras en millones de pesos | C2: Banco de Occidente
B3: Efectivo y reservas en el banco central | C3: 1094
B4: Títulos de deuda | C4: =SUM(C5:C9) -> 2900
B5: Bonos gubernamentales < 1 año (Nivel 1 para HQLA) | C5: 400
B6: Bonos gubernamentales 1-5 años tasa revisable (Nivel 1 para HQLA) | C6: 0
B7: Bonos gubernamentales 1-5 años tasa fija (Nivel 2A para HQLA) | C7: 1500
B8: Bonos corporativos calif AA- o superior tasa fija (Nivel 2A para HQLA) | C8: 1000
B9: Bonos corporativos calif BBB- a A+ tasa fija (nivel 2B para HQLA) | C9: 0
B10: Cartera de crédito | C10: =SUM(C11:C13) -> 17449
B11: Hipotecario | C11: 7538
B12: Consumo (tarjetas de crédito, personales)* | C12: 5714
B13: PYMES | C13: 4197
B14: Activos Fijos | C14: 1028
B15: Otros activos | C15: 37
B16: TOTAL ACTIVO | C16: =C3+C4+C10+C14+C15 -> 22508
B17: Depósitos a la vista | C17: =C18+C19 -> 7817
B18: Minoristas (retail)*** | C18: 3839
B19: De empresas**** | C19: 3978
B20: Depósitos a plazo | C20: =C21+C22 -> 3124
B21: Minoristas (retail)***** | C21: 2179
B22: De empresas | C22: 945
B23: Fondeo mayorista****** | C23: 1016
B24: Bonos emitidos con vencimiento < 1 año | C24: 3000
B25: Bonos emitidos con vencimiento 1-5 años | C25: 2000
B26: Bonos emitidos con vencimiento 5-10 años | C26: 0
B27: TOTAL PASIVO | C27: =C17+C20+C23+C24+C25+C26 -> 16957
B28: Capital Tier 1 | C28: 5551
B29: Capital Tier 2 | C29: 0
B30: TOTAL CAPITAL | C30: =C28+C29 -> 5551
B31: TOTAL PASIVO Y CAPITAL | C31: =C27+C30 -> 22508

Sheet LCR
B2: LCR | C2: =F11/G36 -> 1.6990834
B4: HQLA
C6: Descripción | D6: Ponderación | E6: Monto | F6: Monto Factorizado
C7: Efectivo y reservas en el banco central | D7: 1 | E7: =Datos!C3 -> 1094 | F7: =E7*D7 -> 1094
C8: Nivel 1 para HQLA | D8: 1 | E8: =Datos!C5+Datos!C6 -> 400 | F8: =E8*D8 -> 400
C9: Nivel 2A para HQLA | D9: 0.85 | E9: =Datos!C7+Datos!C8 -> 2500 | F9: =E9*D9 -> 2125
C10: Nivel 2B para HQLA | D10: 0.5 | E10: =Datos!C9 -> 0 | F10: =E10*D10 -> 0
E11: TOTAL | F11: =SUM(F7:F10) -> 3619
B13: SALIDAS NETAS DE EFECTIVO
C15: Descripción | D15: Factor | E15: Ponderaciones | F15: Monto | G15: Monto Factorizado
C16: VISTA
C17: Depósitos minoristas core (vista) | D17: 0.03 | E17: 0.8 | F17: =E17*Datos!C18 -> 3071.2 | G17: =F17*D17 -> 92.136
C18: Depósitos minoristas menos estables (vista) | D18: 0.1 | E18: =1-E17 -> 0.2 | F18: =E18*Datos!C18 -> 767.8 | G18: =F18*D18 -> 76.78
C19: Depósitos operacionales de empresas (vista) | D19: 0.25 | E19: 0.6 | F19: =E19*Datos!C19 -> 2386.8 | G19: =F19*D19 -> 596.7
C20: Depósitos no operacionales de empresas (vista) | D20: 0.4 | E20: 0.4 | F20: =E20*Datos!$C$19 -> 1591.2 | G20: =F20*D20 -> 636.48
C21: Depósitos operacioneles de financieras (vista) | D21: 1 | E21: 0 | F21: =E21*Datos!$C$19 -> 0 | G21: =F21*D21 -> 0
C22: Depósitos no operacioneles de financieras (vista) | D22: 1 | E22: 0 | F22: =E22*Datos!$C$19 -> 0 | G22: =F22*D22 -> 0
C23: PLAZO
C24: Depósitos minoristas core (plazo) | D24: 0.03 | E24: =E17 -> 0.8 | F24: =E24*Datos!C21 -> 1743.2 | G24: =F24*D24 -> 52.296
C25: Depósitos minoristas menos estables (plazo) | D25: 0.1 | E25: =E18 -> 0.2 | F25: =E25*Datos!C21 -> 435.8 | G25: =F25*D25 -> 43.58
C26: Depósitos operacionales de empresas (plazo) | D26: 0.25 | E26: 0 | F26: =E26*Datos!$C$22 -> 0 | G26: =F26*D26 -> 0
C27: Depósitos no operacionales de empresas (plazo) | D27: 0.4 | E27: 1 | F27: =E27*Datos!$C$22 -> 945 | G27: =F27*D27 -> 378
C28: Depósitos operacioneles de financieras (plazo) | D28: 1 | E28: =E21 -> 0 | F28: =E28*Datos!$C$22 -> 0 | G28: =F28*D28 -> 0
C29: Depósitos no operacioneles de financieras (plazo) | D29: 1 | E29: =E22 -> 0 | F29: =E29*Datos!$C$22 -> 0 | G29: =F29*D29 -> 0
C30: FONDEO MAYORISTA
C31: Fondeo mayorista garantizado con HQLA Nivel 1 contraparte no financiera | D31: 0 | E31: 0 | F31: =E31*Datos!$C$23 -> 0 | G31: =F31*D31 -> 0
C32: Fondeo mayorista garantizado con HQLA Nivel 1 contraparte financiera | D32: 0 | E32: 0 | F32: =E32*Datos!$C$23 -> 0 | G32: =F32*D32 -> 0
C33: Fondeo mayorista garantizado con HQLA Nivel 2A contraparte no financiera | D33: 0.15 | E33: 0 | F33: =E33*Datos!$C$23 -> 0 | G33: =F33*D33 -> 0
C34: Fondeo mayorista garantizado con HQLA Nivel 2A contraparte financiera | D34: 0.25 | E34: 1 | F34: =Datos!C23 -> 1016 | G34: =F34*D34 -> 254
C35: Fondeo mayorista sin colateral (sin garantía) | D35: 1 | E35: 0 | F35: =E35*Datos!$C$23 -> 0 | G35: =F35*D35 -> 0
F36: TOTAL | G36: =SUM(G17:G22,G24:G29,G32:G35) -> 2129.972

Sheet NSFT
B2: NSFT | C2: =F18/F33 -> 1.41588
B4: ASF
C6: Descripción | D6: Factor | E6: Monto | F6: Monto Factorizado
C7: Capital Tier 1 y Tier 2 | D7: 1 | E7: =Datos!C30 -> 5551 | F7: =D7*E7 -> 5551
C8: Pasivos con plazo residual mayor a 1 año | D8: 1 | E8: =Datos!C25+Datos!C26 -> 2000 | F8: =D8*E8 -> 2000
C9: Depósitos minoristas estables (core) | D9: 0.95 | E9: =LCR!F17+LCR!F24 -> 4814.4 | F9: =D9*E9 -> 4573.68
C10: Depósitos minoristas menos estables (volátiles) | D10: 0.9 | E10: =LCR!F18+LCR!F25 -> 1203.6 | F10: =D10*E10 -> 1083.24
C11: Depósitos operacionales de empresas no financieras | D11: 0.75 | E11: =LCR!F19+LCR!F26 -> 2386.8 | F11: =D11*E11 -> 1790.1
C12: Depósitos no operacionales de empresas no financieras | D12: 0 | E12: =LCR!F20+LCR!F27 -> 2536.2 | F12: =D12*E12 -> 0
C13: Depósitos operacionales de empresas financieras | D13: 0.5 | E13: =LCR!F21+LCR!F28 -> 0 | F13: =D13*E13 -> 0
C14: Depósitos no operacionales de empresas financieras | D14: 0 | E14: =LCR!F22+LCR!F29 -> 0 | F14: =D14*E14 -> 0
C15: Fondeo mayorista contrapartes no financieras con colateral | D15: 0.6 | E15: =LCR!F31+LCR!F33 -> 0 | F15: =D15*E15 -> 0
C16: Fondeo mayorista contrapartes financieras con colateral | D16: 0.4 | E16: =LCR!F32+LCR!F34 -> 1016 | F16: =D16*E16 -> 406.4
C17: Fondeo mayorista sin colateral | D17: 0 | E17: =LCR!F35 -> 0 | F17: =D17*E17 -> 0
E18: TOTAL | F18: =SUM(F7:F17) -> 15404.42
B21: RSF
C23: Descripción | D23: Factor | E23: Monto | F23: Monto Factorizado
C24: Efectivo y depósitos en el banco central | D24: 0 | E24: =LCR!E7 -> 1094 | F24: =E24*D24 -> 0
C25: HQLA nivel 1 | D25: 0.05 | E25: =LCR!E8 -> 400 | F25: =E25*D25 -> 20
C26: HQLA nivel 2A | D26: 0.15 | E26: =LCR!E9 -> 2500 | F26: =E26*D26 -> 375
C27: HQLA nivel 2B | D27: 0.5 | E27: =LCR!E10 -> 0 | F27: =E27*D27 -> 0
C28: Hipotecarios | D28: 0.65 | E28: =Datos!C11 -> 7538 | F28: =E28*D28 -> 4899.7
C29: Créditos a consumo | D29: 0.5 | E29: =Datos!C12 -> 5714 | F29: =E29*D29 -> 2857
C30: Créditos PYME | D30: 0.65 | E30: =Datos!C13 -> 4197 | F30: =E30*D30 -> 2728.05
C31: Créditos a empresas no financieras (corporativos) largo plazo | D31: 0.65 | E31: 0 | F31: =E31*D31 -> 0
C32: Créditos a instituciones financieras (largo plazo) | D32: 1 | E32: 0 | F32: =E32*D32 -> 0
E33: TOTAL | F33: =SUM(F24:F32) -> 10879.75

Sheet NII
C2: TIIE Fondeo | D2: 0.0675 | F2: Cambio en TIIE | G2: 0.005
C4: Total Ingresos | D4: =E22 -> 4432.0426 | F4: Total Ingresos | G4: =H22 -> 40.1269 | I4: Total Activos Variables | K4: =C20+C19*0.67+C13 -> 8025.38
C5: Total Egresos | D5: =E38 -> 585.593 | F5: Total Egresos | G5: =H38 -> 40.62 | I5: Total Pasivos Variables | K5: =C29+C30+C32+C33 -> 8124
C6: NII | D6: =D4-D5 -> 3846.4496 | F6: Delta NII | G6: =G4-G5 -> -0.4931 | I6: Brecha | K6: =ABS(K4-K5) -> 98.62
C7: ROE | D7: =D6/C36 -> 0.69292912 | F7: Delta ROE | G7: =G6/C36 -> -8.8830841e-05
B9: cifras en millones de pesos | C9: Banco de Occidente | D9: Tasa | E9: Ingresos | G9: Delta Tasa | H9: Delta Ingreso
B10: Efectivo y reservas en el banco central | C10: =Datos!C3 -> 1094
B11: Títulos de deuda | C11: =Datos!C4 -> 2900
B12: Bonos gubernamentales < 1 año (Nivel 1 para HQLA) | C12: =Datos!C5 -> 400 | D12: 0.0718 | E12: =C12*D12 -> 28.72 | G12: 0 | H12: =C12*G12 -> 0
B13: Bonos gubernamentales 1-5 años tasa revisable (Nivel 1 para HQLA) | C13: =Datos!C6 -> 0 | D13: =D2+0.0019 -> 0.0694 | E13: =C13*D13 -> 0 | G13: =G2 -> 0.005 | H13: =C13*G13 -> 0
B14: Bonos gubernamentales 1-5 años tasa fija (Nivel 2A para HQLA) | C14: =Datos!C7 -> 1500 | D14: 0.0832 | E14: =C14*D14 -> 124.8 | G14: 0 | H14: =C14*G14 -> 0
B15: Bonos corporativos calif AA- o superior tasa fija (Nivel 2A para HQLA) | C15: =Datos!C8 -> 1000 | D15: 0.097 | E15: =C15*D15 -> 97 | G15: 0 | H15: =C15*G15 -> 0
B16: Bonos corporativos calif BBB- a A+ tasa fija (nivel 2B para HQLA) | C16: =Datos!C9 -> 0 | D16: 0 | E16: =C16*D16 -> 0 | G16: 0 | H16: =C16*G16 -> 0
B17: Cartera de crédito | C17: =Datos!C10 -> 17449 | E17: 0
B18: Hipotecario | C18: =Datos!C11 -> 7538 | D18: 0.1086 | E18: =C18*D18 -> 818.6268 | G18: 0 | H18: =C18*G18 -> 0
B19: Consumo (tarjetas de crédito, de nómina, personales)* | C19: =Datos!C12 -> 5714 | D19: =0.67*(D2+0.48)+0.33*(0.21) -> 0.436125 | E19: =C19*D19 -> 2492.0183 | G19: =G2*0.67 -> 0.00335 | H19: =C19*G19 -> 19.1419
B20: PYMES | C20: =Datos!C13 -> 4197 | D20: =D2+0.14 -> 0.2075 | E20: =C20*D20 -> 870.8775 | G20: =G2 -> 0.005 | H20: =C20*G20 -> 20.985
B21: Activos Fijos | C21: =Datos!C14 -> 1028
B22: Otros activos | C22: =Datos!C15 -> 37 | D22: TOTAL | E22: =SUM(E12:E20) -> 4432.0426 | G22: TOTAL | H22: =SUM(H12:H20) -> 40.1269
B24: TOTAL ACTIVO | C24: =C10+C11+C17+C21+C22 -> 22508 | D24: Tasa | E24: Egresos | G24: Delta Tasa | H24: Delta Egresos
B25: Depósitos a la vista | C25: =Datos!C17 -> 7817
B26: Minoristas (retail)*** | C26: =Datos!C18 -> 3839 | D26: 0 | E26: =C26*D26 -> 0 | G26: 0 | H26: =C26*G26 -> 0
B27: De empresas**** | C27: =Datos!C19 -> 3978 | D27: 0 | E27: =C27*D27 -> 0 | G27: 0 | H27: =C27*G27 -> 0
B28: Depósitos a plazo | C28: =Datos!C20 -> 3124
B29: Minoristas (retail)***** | C29: =Datos!C21 -> 2179 | D29: =0.5*(0.03)+0.5*(0.04) -> 0.035 | E29: =C29*D29 -> 76.265 | G29: =G2 -> 0.005 | H29: =C29*G29 -> 10.895
B30: De empresas | C30: =Datos!C22 -> 945 | D30: =0.8*(0.03)+0.2*(0.04) -> 0.032 | E30: =C30*D30 -> 30.24 | G30: =G2 -> 0.005 | H30: =C30*G30 -> 4.725
B31: Fondeo mayorista****** | C31: =Datos!C23 -> 1016 | D31: 0.068 | E31: =C31*D31 -> 69.088 | G31: 0 | H31: =C31*G31 -> 0
B32: Bonos emitidos con vencimiento < 1 año | C32: =Datos!C24 -> 3000 | D32: =D2+0.0125 -> 0.08 | E32: =C32*D32 -> 240 | G32: =G2 -> 0.005 | H32: =C32*G32 -> 15
B33: Bonos emitidos con vencimiento 1-5 años | C33: =Datos!C25 -> 2000 | D33: =D2+0.0175 -> 0.085 | E33: =C33*D33 -> 170 | G33: =G2 -> 0.005 | H33: =C33*G33 -> 10
B34: Bonos emitidos con vencimiento 5-10 años | C34: =Datos!C26 -> 0 | D34: 0 | E34: =C34*D34 -> 0 | G34: 0 | H34: =C34*G34 -> 0
B35: TOTAL PASIVO | C35: =C25+C28+C31+C32+C33+C34 -> 16957
B36: Capital Tier 1 | C36: =Datos!C28 -> 5551
B37: Capital Tier 2 | C37: =Datos!C29 -> 0 | D37: 0 | E37: =C37*D37 -> 0 | G37: 0 | H37: =C37*G37 -> 0
B38: TOTAL CAPITAL | C38: =C36+C37 -> 5551 | D38: TOTAL | E38: =SUM(E26:E37) -> 585.593 | G38: TOTAL | H38: =SUM(H26:H37) -> 40.62
B39: TOTAL PASIVO Y CAPITAL | C39: =C35+C38 -> 22508
